setup.py
kegbot/__init__.py
kegbot/api/__init__.py
kegbot/api/api_pb2.py
kegbot/api/exceptions.py
kegbot/api/kbapi.py
kegbot/api/models_pb2.py
kegbot/api/protoutil.py
kegbot/api/util.py
kegbot_api.egg-info/PKG-INFO
kegbot_api.egg-info/SOURCES.txt
kegbot_api.egg-info/dependency_links.txt
kegbot_api.egg-info/namespace_packages.txt
kegbot_api.egg-info/requires.txt
kegbot_api.egg-info/top_level.txt