Metadata-Version: 2.1
Name: kegbot-api
Version: 1.3.1
Summary: Kegboard API client library
Home-page: https://kegbot.org/
Author: The Kegbot Project Contributors
Author-email: info@kegbot.org
License: MIT
Platform: UNKNOWN
